kimage/__init__.py
kimage-0.1.dist-info/entry_points.txt
kimage-0.1.dist-info/WHEEL
kimage-0.1.dist-info/METADATA
kimage-0.1.dist-info/RECORD
