Metadata-Version: 2.1
Name: kimage
Version: 0.1
Summary: 一个好用的图像处理库
Keywords: 
Author-email: jutooy <jutooy@qq.com>
Classifier: License :: OSI Approved :: Apache Software License
